testutils/__init__.py
testutils/testutils.py
snowconvert_test_utils-0.2.dist-info/METADATA
snowconvert_test_utils-0.2.dist-info/WHEEL
snowconvert_test_utils-0.2.dist-info/top_level.txt
snowconvert_test_utils-0.2.dist-info/RECORD
